itemsubjector.py
itemsubjector-0.3.4.dist-info/LICENSE
itemsubjector-0.3.4.dist-info/WHEEL
itemsubjector-0.3.4.dist-info/METADATA
itemsubjector-0.3.4.dist-info/RECORD
