Metadata-Version: 2.1
Name: itemsubjector
Version: 0.3.4
Summary: CLI-tool to easily add "main subject" aka topics in bulk to groups of items on Wikidata
Home-page: https://github.com/dpriskorn/ItemSubjector
License: GPLv3+
Keywords: wikidata,subjects,entity linking,scientific graph,linked open data,open scientific data
Author: Dennis Priskorn
Author-email: 68460690+dpriskorn@users.noreply.github.com
Requires-Python: >=3.8,<3.11
Classifier: License :: OSI Approved :: GNU General Public License v3 or later (GPLv3+)
Classifier: License :: Other/Proprietary License
Classifier: Operating System :: OS Independent
Classifier: Programming Language :: Python :: 3
Classifier: Programming Language :: Python :: 3.8
Classifier: Programming Language :: Python :: 3.9
Classifier: Programming Language :: Python :: 3.10
Classifier: Programming Language :: Python :: 3
Classifier: Topic :: Utilities
Requires-Dist: console-menu (>=0.7.1,<0.8.0)
Requires-Dist: pandas (>=1.5.0,<2.0.0)
Requires-Dist: pydantic (>=1.10.2,<2.0.0)
Requires-Dist: rich (>=12.5.1,<13.0.0)
Requires-Dist: setuptools (>=65.4.1,<66.0.0)
Requires-Dist: wikibaseintegrator (>=0.12.1,<0.13.0)
Project-URL: Repository, https://github.com/dpriskorn/ItemSubjector
